huluwa_hjs_mcp_demo/__init__.py
huluwa_hjs_mcp_demo-0.1.0.dist-info/WHEEL
huluwa_hjs_mcp_demo-0.1.0.dist-info/entry_points.txt
huluwa_hjs_mcp_demo-0.1.0.dist-info/METADATA
huluwa_hjs_mcp_demo-0.1.0.dist-info/RECORD
